{"meta":{"rok":2012,"typ":"wykonanie","jednostka":"tys. zł","porownanie":"plan z ustawy budżetowej vs wykonanie","zrodlo":"Ministerstwo Finansów — Sprawozdanie z wykonania budżetu państwa za okres 1.01–31.12.2012 r. (zestawienie ogólne z wykonania budżetu; dochody budżetu państwa — zestawienie ogółem, str. 1.1; wydatki budżetu państwa wg działów, str. 2.1–2.4).","uwaga":"Plan = ustawa budżetowa na 2012 r. (Dz.U. 2012 poz. 273): dochody 293,8 mld, wydatki 328,8 mld, deficyt 35,0 mld zł. Łączny limit wydatków nie zmienił się w ciągu roku (budżet po zmianach = ustawa na poziomie ogółem). MF liczy stopień wykonania względem planu po zmianach (po uruchomieniu rezerw), więc w pojedynczych działach bywa >100% tam, gdzie dosypano rezerwy celowe. Tabela działów obejmuje też działy 400 i 756, nieobecne w pierwotnym planie.","zrodlo_dochody":"MF — sprawozdanie z wykonania budżetu 2012, dochody budżetu państwa — zestawienie ogółem (str. 1.1). 'Inne' liczone jako reszta do dochodów ogółem."},"wykonanie":{"wydatki":318001861,"dochody":287595114,"deficyt":30406746},"dochody":{"VAT":120000697,"Akcyza":60449853,"CIT":25145736,"PIT":39809425},"dzialy":{"010":10438071,"020":11513,"050":236599,"100":551851,"150":1043089,"400":1379,"500":650360,"550":20607,"600":9669092,"630":44866,"700":2571151,"710":1135420,"720":187450,"730":4849533,"750":12378672,"751":1938680,"752":20085935,"753":75958919,"754":13079598,"755":10133484,"756":4898,"757":42108822,"758":68418786,"801":1846816,"803":12402048,"851":7241984,"852":13926821,"853":3479898,"854":509031,"900":480339,"921":1716955,"925":97219,"926":781975}}